__init__.py
cfa/__init__.py
cfa/__main__.py
cfa/apply_template_option.py
cfa/fastapi-app/.gitignore
cfa/fastapi-app/Dockerfile
cfa/fastapi-app/Pipfile
cfa/fastapi-app/Pipfile.lock
cfa/fastapi-app/README.md
cfa/fastapi-app/create_git_hooks.sh
cfa/fastapi-app/docker-compose.yml
cfa/fastapi-app/env_example
cfa/fastapi-app/init_db.sh
cfa/fastapi-app/main.py
cfa/fastapi-app/app/__init__.py
cfa/fastapi-app/app/api/__init__.py
cfa/fastapi-app/app/api/deps.py
cfa/fastapi-app/app/api/v1/__init__.py
cfa/fastapi-app/app/api/v1/endpoints/__init__.py
cfa/fastapi-app/app/api/v1/endpoints/item.py
cfa/fastapi-app/app/core/__init__.py
cfa/fastapi-app/app/core/config.py
cfa/fastapi-app/app/crud/__init__.py
cfa/fastapi-app/app/crud/base.py
cfa/fastapi-app/app/crud/crud_item.py
cfa/fastapi-app/app/database/__init__.py
cfa/fastapi-app/app/database/base.py
cfa/fastapi-app/app/database/initialize.py
cfa/fastapi-app/app/database/session.py
cfa/fastapi-app/app/models/__init__.py
cfa/fastapi-app/app/models/item.py
cfa/fastapi-app/app/schemas/__init__.py
cfa/fastapi-app/app/schemas/item.py
cfa/fastapi-app/app/tests/__init__.py
cfa/fastapi-app/app/tests/conftest.py
cfa/fastapi-app/app/tests/api/__init__.py
cfa/fastapi-app/app/tests/api/v1/__init__.py
cfa/fastapi-app/app/tests/api/v1/test_item.py
cfa/fastapi-app/git_hooks/pre-commit.sh
cfa/fastapi-app/git_hooks/pre-push.sh
cfa/options/__init__.py
cfa/options/auth/__init__.py
cfa/options/auth/backend/app-api-deps.py
cfa/options/auth/backend/app-api-v1-__init__.py
cfa/options/auth/backend/app-api-v1-endpoints-auth.py
cfa/options/auth/backend/app-api-v1-endpoints-item.py
cfa/options/auth/backend/app-core-config.py
cfa/options/auth/self/__init__.py
cfa/options/auth/self/app-api-deps.py
cfa/options/auth/self/app-api-v1-__init__.py
cfa/options/auth/self/app-api-v1-endpoints-auth.py
cfa/options/auth/self/app-api-v1-endpoints-user.py
cfa/options/auth/self/app-core-config.py
cfa/options/auth/self/app-crud-crud_user.py
create_fastapi_app-0.4.4.dist-info/LICENSE
create_fastapi_app-0.4.4.dist-info/METADATA
create_fastapi_app-0.4.4.dist-info/WHEEL
create_fastapi_app-0.4.4.dist-info/entry_points.txt
create_fastapi_app-0.4.4.dist-info/top_level.txt
create_fastapi_app-0.4.4.dist-info/RECORD
