Metadata-Version: 2.1
Name: create-fastapi-app
Version: 0.4.4
Summary: Wrapper for initializing FastAPI projects - Create Fastapi App
Author: Tomas Sladecek
License: MIT License
Project-URL: Homepage, https://github.com/tsladecek/create-fastapi-app
Classifier: Programming Language :: Python :: 3
Classifier: Operating System :: OS Independent
Requires-Python: >=3.6
License-File: LICENSE
Requires-Dist: typer (<1,>=0.6)
Requires-Dist: colorama (<1,>=0.4)
Requires-Dist: rich (<13,>=12.6)
Requires-Dist: shellingham (<2,>=1.5)
